{"@class":"PhysicsBody","id":{"uuid":"D52353AF-43E5-4C6F-A3A3-45AE55105571"},"physBodyType":"triggerVolume","physSurfaceType":"defaultSurfaceType","mass":0.0010000000474974514,"friction":1.0,"bounciness":0.5,"lockPositionX":false,"lockPositionY":false,"lockPositionZ":false,"lockRotationX":false,"lockRotationY":false,"lockRotationZ":false,"gravity":{"values":[0.0,0.0,0.0]},"useCustomGravity":false,"useCCD":false,"ccdSweptSphereRadius":0.0,"ccdMotionThreshold":0.0,"useLocalInitialVelocities":false,"initLinearVelocity":{"values":[0.0,0.0,0.0]},"initAngularVelocity":{"values":[0.0,0.0,0.0]}}